ProgressIter/__init__.py
ProgressIter-0.4.0.dist-info/LICENSE
ProgressIter-0.4.0.dist-info/METADATA
ProgressIter-0.4.0.dist-info/WHEEL
ProgressIter-0.4.0.dist-info/top_level.txt
ProgressIter-0.4.0.dist-info/RECORD
