Metadata-Version: 2.1
Name: ProgressIter
Version: 0.4.0
Summary: A simple wrapper of any Iterator or Iterable
Home-page: https://github.com/Alex-Horseman/ProgressIter
Author: Bojack
Author-email: mayan2017@buaa.edu.cn
License: UNKNOWN
Platform: UNKNOWN
Classifier: Programming Language :: Python :: 3
Classifier: License :: OSI Approved :: MIT License
Classifier: Operating System :: Microsoft :: Windows
Requires-Python: >=3.6
